eccore/__init__.py
eccore/_modidx.py
eccore/core.py
eccore/dev_utils.py
eccore/ipython.py
eccore/plotting.py
eccore-0.0.4.dist-info/LICENSE
eccore-0.0.4.dist-info/METADATA
eccore-0.0.4.dist-info/WHEEL
eccore-0.0.4.dist-info/entry_points.txt
eccore-0.0.4.dist-info/top_level.txt
eccore-0.0.4.dist-info/RECORD
