Metadata-Version: 2.1
Name: eccore
Version: 0.0.4
Summary: Functions and classes I use often, inspired by fastcore
Home-page: https://github.com/vtecftwy/eccore
Author: vtecftwy
Author-email: github@procurasia.com
License: MIT License
Keywords: nbdev jupyter notebook python
Classifier: Development Status :: 4 - Beta
Classifier: Intended Audience :: Developers
Classifier: Natural Language :: English
Classifier: Programming Language :: Python :: 3.9
Classifier: Programming Language :: Python :: 3.10
Classifier: License :: OSI Approved :: MIT License
Requires-Python: >=3.9
License-File: LICENSE
Requires-Dist: fastcore
Requires-Dist: matplotlib
Requires-Dist: numpy
Requires-Dist: pandas
Requires-Dist: IPython
Provides-Extra: dev
Requires-Dist: nbdev ; extra == 'dev'
